garpix_menu/MANIFEST.in
garpix_menu/README.md
garpix_menu/README.rst
garpix_menu/__init__.py
garpix_menu/apps.py
garpix_menu/context_processors.py
garpix_menu/serializers.py
garpix_menu/setup.py
garpix_menu/tests.py
garpix_menu/urls.py
garpix_menu/utils.py
garpix_menu/validators.py
garpix_menu/views.py
garpix_menu/__pycache__/__init__.cpython-38.pyc
garpix_menu/__pycache__/apps.cpython-38.pyc
garpix_menu/__pycache__/context_processors.cpython-38.pyc
garpix_menu/__pycache__/serializers.cpython-38.pyc
garpix_menu/__pycache__/tests.cpython-38.pyc
garpix_menu/__pycache__/utils.cpython-38.pyc
garpix_menu/__pycache__/validators.cpython-38.pyc
garpix_menu/admin/__init__.py
garpix_menu/admin/menu_item.py
garpix_menu/admin/__pycache__/__init__.cpython-38.pyc
garpix_menu/admin/__pycache__/menu_item.cpython-38.pyc
garpix_menu/locale/__init__.py
garpix_menu/locale/en/LC_MESSAGES/django.mo
garpix_menu/locale/en/LC_MESSAGES/django.po
garpix_menu/mixins/__init__.py
garpix_menu/mixins/link_mixin.py
garpix_menu/mixins/__pycache__/__init__.cpython-38.pyc
garpix_menu/mixins/__pycache__/link_mixin.cpython-38.pyc
garpix_menu/models/__init__.py
garpix_menu/models/menu_item.py
garpix_menu/models/__pycache__/__init__.cpython-38.pyc
garpix_menu/models/__pycache__/menu_item.cpython-38.pyc
garpix_menu/translation/__init__.py
garpix_menu/translation/menu.py
garpix_menu/translation/__pycache__/__init__.cpython-38.pyc
garpix_menu/translation/__pycache__/menu.cpython-38.pyc
garpix_menu-1.17.1.dist-info/METADATA
garpix_menu-1.17.1.dist-info/WHEEL
garpix_menu-1.17.1.dist-info/top_level.txt
garpix_menu-1.17.1.dist-info/RECORD
