Metadata-Version: 2.1
Name: garpix-menu
Version: 1.17.1
Author: Garpix LTD
Author-email: info@garpix.com
License: MIT
Project-URL: Documentation, https://docs.garpixcms.ru/packages/garpix_menu/
Project-URL: GitHub, https://github.com/garpixcms/garpix_menu/
Project-URL: Changelog, https://github.com/garpixcms/garpix_menu/blob/master/CHANGELOG.md/
Classifier: Development Status :: 4 - Beta
Classifier: Environment :: Web Environment
Classifier: Intended Audience :: Developers
Classifier: License :: OSI Approved :: MIT License
Classifier: Operating System :: OS Independent
Classifier: Programming Language :: Python
Classifier: Framework :: Django
Classifier: Programming Language :: Python :: 3.6
Classifier: Programming Language :: Python :: 3.7
Classifier: Programming Language :: Python :: 3.8
Requires-Dist: Django (<5,>=1.11)
Requires-Dist: django-mptt (>=0.9.1)
Requires-Dist: django-modeltranslation (>=0.16.2)
Requires-Dist: garpix-page (>=2.42.0-rc2)
Requires-Dist: garpix-utils (>=1.8.0)
